openai_agents_opentelemetry/__init__.py
openai_agents_opentelemetry/_version.py
openai_agents_opentelemetry/opentelemetry_processor.py
openai_agents_opentelemetry-0.2.1.dist-info/METADATA
openai_agents_opentelemetry-0.2.1.dist-info/WHEEL
openai_agents_opentelemetry-0.2.1.dist-info/licenses/LICENSE
openai_agents_opentelemetry-0.2.1.dist-info/RECORD
