Metadata-Version: 2.4
Name: openai-agents-opentelemetry
Version: 0.2.1
Summary: OpenTelemetry tracing processor for the OpenAI Agents SDK
Project-URL: Homepage, https://github.com/damianoneill/openai-agents-opentelemetry
Project-URL: Repository, https://github.com/damianoneill/openai-agents-opentelemetry
Author: Damian ONeill
License: MIT
License-File: LICENSE
Keywords: agents,observability,openai,opentelemetry,tracing
Classifier: Development Status :: 4 - Beta
Classifier: Intended Audience :: Developers
Classifier: License :: OSI Approved :: MIT License
Classifier: Programming Language :: Python :: 3
Classifier: Programming Language :: Python :: 3.11
Classifier: Programming Language :: Python :: 3.12
Classifier: Programming Language :: Python :: 3.13
Requires-Python: >=3.11
Requires-Dist: openai-agents>=0.1.0
Requires-Dist: opentelemetry-api>=1.20.0
Requires-Dist: opentelemetry-sdk>=1.20.0
Provides-Extra: dev
Requires-Dist: commitizen>=3.0.0; extra == 'dev'
Requires-Dist: mypy>=1.19.0; extra == 'dev'
Requires-Dist: pre-commit>=3.0.0; extra == 'dev'
Requires-Dist: pytest-asyncio>=0.21.0; extra == 'dev'
Requires-Dist: pytest-cov>=4.0.0; extra == 'dev'
Requires-Dist: pytest>=7.0.0; extra == 'dev'
Requires-Dist: ruff>=0.14.0; extra == 'dev'
